filprofiler-2024.11.2.data/data/share/jupyter/kernels/filprofile/logo-64x64.png
filprofiler-2024.11.2.data/data/share/jupyter/kernels/filprofile/logo-32x32.png
filprofiler-2024.11.2.data/data/share/jupyter/kernels/filprofile/kernel.json
filprofiler/_utils.py
filprofiler/_report.py
filprofiler/_testing.py
filprofiler/__init__.py
filprofiler/api.py
filprofiler/_ipython.py
filprofiler/_script.py
filprofiler/_cachegrind.py
filprofiler/_version.py
filprofiler/licenses.txt
filprofiler/__main__.py
filprofiler/_filpreload.cpython-311-aarch64-linux-gnu.so
filprofiler/_tracer.py
filprofiler-2024.11.2.dist-info/top_level.txt
filprofiler-2024.11.2.dist-info/RECORD
filprofiler-2024.11.2.dist-info/LICENSE
filprofiler-2024.11.2.dist-info/entry_points.txt
filprofiler-2024.11.2.dist-info/METADATA
filprofiler-2024.11.2.dist-info/WHEEL
