Metadata-Version: 2.1
Name: filprofiler
Version: 2024.11.2
Summary: A memory profiler for data batch processing applications.
Home-page: https://pythonspeed.com/fil/
Maintainer: Itamar Turner-Trauring
Maintainer-email: itamar@pythonspeed.com
License: Apache 2.0
Classifier: Intended Audience :: Developers
Classifier: License :: OSI Approved :: Apache Software License
Classifier: Operating System :: MacOS
Classifier: Operating System :: POSIX :: Linux
Classifier: Programming Language :: Python
Classifier: Programming Language :: Python :: 3
Classifier: Programming Language :: Python :: 3.9
Classifier: Programming Language :: Python :: 3.10
Classifier: Programming Language :: Python :: 3.11
Classifier: Programming Language :: Python :: 3.12
Classifier: Programming Language :: Python :: 3.13
Classifier: Programming Language :: Python :: Implementation :: CPython
Requires-Python: >=3.9
License-File: LICENSE
Requires-Dist: threadpoolctl
Provides-Extra: dev
Requires-Dist: pytest; extra == "dev"
Requires-Dist: pampy; extra == "dev"
Requires-Dist: numpy>1; extra == "dev"
Requires-Dist: cython; extra == "dev"
Requires-Dist: black; extra == "dev"
Requires-Dist: towncrier; extra == "dev"
Requires-Dist: wheel; extra == "dev"
Requires-Dist: auditwheel; extra == "dev"
Requires-Dist: twine; extra == "dev"
Requires-Dist: ipython; extra == "dev"
Requires-Dist: ipykernel; extra == "dev"
Requires-Dist: nbconvert; extra == "dev"
Requires-Dist: jinja2<3.1; extra == "dev"
Requires-Dist: numexpr; extra == "dev"
Requires-Dist: blosc; extra == "dev"
Requires-Dist: psutil; extra == "dev"
Requires-Dist: flake8; extra == "dev"
Requires-Dist: meson; extra == "dev"
Requires-Dist: ninja; extra == "dev"
